Metadata-Version: 1.1
Name: thesamet.playpants
Version: 0.1.1
Summary: Play plugin for Pants
Home-page: https://github.com/thesamet/playpants
Author: Nadav Sr. Samet
Author-email: nadav@thesamet.com
License: Apache License, Version 2.0
Platform: UNKNOWN
Classifier: Intended Audience :: Developers
Classifier: License :: OSI Approved :: Apache Software License
Classifier: Operating System :: OS Independent
Classifier: Programming Language :: Python
